mygp_cli/__init__.py
mygp_cli/auth_info.py
mygp_cli/main.py
mygp_cli-0.0.3.dist-info/entry_points.txt
mygp_cli-0.0.3.dist-info/WHEEL
mygp_cli-0.0.3.dist-info/METADATA
mygp_cli-0.0.3.dist-info/RECORD
