Metadata-Version: 2.1
Name: mygp-cli
Version: 0.0.3
Summary: Command-line interface for the Marketplace Sandbox API
Author: Igor Brejc
Author-email: igor.brejc@nfcsb.com
Requires-Python: >=3.7,<4.0
Classifier: Programming Language :: Python :: 3
Classifier: Programming Language :: Python :: 3.7
Classifier: Programming Language :: Python :: 3.8
Requires-Dist: requests (>=2.23.0,<3.0.0)
